alxcheck/__init__.py
alxcheck/main.py
alxcheck/checks/__init__.py
alxcheck/checks/c.py
alxcheck/checks/general.py
alxcheck/checks/javascript.py
alxcheck/checks/python.py
alxcheck/tests/__init__.py
alxcheck/tests/base_test.py
alxcheck/tests/test_general.py
alxcheck/tests/test_helpers.py
alxcheck/tests/test_javascript.py
alxcheck/tests/test_python.py
alxcheck/utils/__init__.py
alxcheck/utils/error_logging.py
alxcheck/utils/helpers.py
alxcheck-0.1.3.dist-info/LICENSE
alxcheck-0.1.3.dist-info/METADATA
alxcheck-0.1.3.dist-info/WHEEL
alxcheck-0.1.3.dist-info/entry_points.txt
alxcheck-0.1.3.dist-info/top_level.txt
alxcheck-0.1.3.dist-info/RECORD
