Metadata-Version: 2.1
Name: alxcheck
Version: 0.1.3
Summary: ALX text suite. Shell Utility that checks files for ALX's Project Requirements. Including: General, C, JavaScript and Python projects
Author-email: Emmanuel Nwafor <nwaforemmanuel005@gmail.com>
License: MIT
Project-URL: Homepage, https://github.com/Emmo00/alxcheck.git
Project-URL: Bug Tracker, https://github.com/Emmo00/alxcheck/issues
Keywords: alx,alx test,test,checks,test suite,green squares
Classifier: Environment :: Console
Classifier: Intended Audience :: Developers
Classifier: License :: OSI Approved :: MIT License
Classifier: Operating System :: OS Independent
Classifier: Programming Language :: Python
Classifier: Programming Language :: Python :: 3
Requires-Python: >=3.7
License-File: LICENSE
Requires-Dist: pycodestyle
Requires-Dist: colorama
